[
  {
    "id": "107156011",
    "name": "Airport"
  },
  {
    "id": "11937",
    "name": "Commercial"
  },
  {
    "id": "107151011",
    "name": "Engines"
  },
  {
    "id": "11939",
    "name": "General"
  },
  {
    "id": "107154011",
    "name": "Helicopters"
  },
  {
    "id": "11941",
    "name": "History"
  },
  {
    "id": "11943",
    "name": "Pictorial"
  },
  {
    "id": "745504",
    "name": "Piloting & Flight Instruction"
  },
  {
    "id": "11945",
    "name": "Repair & Maintenance"
  },
  {
    "id": "107153011",
    "name": "Safety"
  }
]