{
  "id": "11657",
  "name": "Professional",
  "level": 2,
  "parentId": "5267710011",
  "isLeaf": false,
  "path": [
    "8975347011",
    "Test Preparation",
    "Professional"
  ],
  "nodes": [],
  "leafs": [
    {
      "id": "11659",
      "name": "ASVAB (Armed Forces)"
    },
    {
      "id": "5744308011",
      "name": "Bar Exam"
    },
    {
      "id": "11661",
      "name": "CPA"
    },
    {
      "id": "11663",
      "name": "Civil Service"
    },
    {
      "id": "227627",
      "name": "Medical"
    },
    {
      "id": "17745840011",
      "name": "NCLEX"
    },
    {
      "id": "227665",
      "name": "Nursing"
    },
    {
      "id": "377568011",
      "name": "PMP Exam"
    },
    {
      "id": "11695",
      "name": "Professional"
    },
    {
      "id": "11664",
      "name": "Teaching"
    },
    {
      "id": "17745839011",
      "name": "USMLE (United States Medical Licensure Examination)"
    },
    {
      "id": "11666",
      "name": "Vocational Tests"
    }
  ]
}