{
  "id": "12292",
  "name": "Catholicism",
  "level": 3,
  "parentId": "16009761",
  "isLeaf": false,
  "path": [
    "22",
    "Christian Books & Bibles",
    "Christian Denominations & Sects",
    "Catholicism"
  ],
  "nodes": [],
  "leafs": [
    {
      "id": "12295",
      "name": "General"
    },
    {
      "id": "172803",
      "name": "Mariology"
    },
    {
      "id": "12300",
      "name": "Popes & the Vatican"
    },
    {
      "id": "12302",
      "name": "Roman Catholicism"
    },
    {
      "id": "12304",
      "name": "Saints"
    },
    {
      "id": "12306",
      "name": "Self Help"
    },
    {
      "id": "12455",
      "name": "Theology"
    }
  ]
}